{
  "title": "دوازدهم - فنی و حرفه‌ای",
  "books": {
    "1": {
      "riazi": {
        "title": "ریاضی",
        "icon": "assets/images/icon-darsha/riazi1.png",
        "cover": "assets/images/book-covers/grade12/fani/riazi.png",
        "chapter_type": "فصل",
        "chapters": {
          "1": {
            "title": "فصل 1: حسابان"
          },
          "2": {
            "title": "فصل 2: هندسه"
          }
        }
      },
      "dini": {
        "title": "دینی",
        "icon": "",
        "cover": "",
        "chapter_type": "درس",
        "chapters": {
          "1": {
            "title": "هستی بخش"
          },
          "2": {
            "title": "یگانۀ بی همتا"
          },
          "3": {
            "title": "توحید و سبک زندگی"
          },
          "4": {
            "title": "فقط برای تو"
          },
          "5": {
            "title": "قدرت پرواز"
          },
          "6": {
            "title": "سنت های خداوند در زندگی"
          },
          "7": {
            "title": "بازگشت"
          },
          "8": {
            "title": "زندگی در دنیای امروز و عمل به احکام الهی"
          },
          "9": {
            "title": "پایه های استوار"
          },
          "10": {
            "title": "تمدن جدید و مسئولیت ما"
          }
        }
      }
    },
    "2": {
      "arabi": {
        "title": "عربی، زبان قر آن 3",
        "icon": "",
        "cover": "",
        "chapter_type": "درس",
        "chapters": {
          "1": {
            "title": "اَلدَّرْسُ ا لْْأَوَّلُ"
          },
          "2": {
            "title": "اَلدَّرْسُ الثّاني"
          },
          "3": {
            "title": "اَلدَّرْسُ الثّالِثُ"
          },
          "4": {
            "title": "اَلدَّرْسُ الرّابِعُ"
          }
        }
      }
    },
    "3": {
      "farsi": {
        "title": "فارسی و نگارش 3",
        "icon": "",
        "cover": "",
        "chapter_type": "درس",
        "chapters": {
          "1": {
            "title": "درس یکم: شُکرِ نعمت"
          },
          "2": {
            "title": "درس دوم: خاطره نگاری"
          },
          "3": {
            "title": "درس سوم: دماوندیه"
          },
          "4": {
            "title": "درس چهارم: نگارش ادبی 1 : نثر ادبی"
          },
          "5": {
            "title": "درس پنجم: در حقیقت عشق"
          },
          "6": {
            "title": "درس ششم: نگارش ادبی 2 : قطعۀ ادبی"
          },
          "7": {
            "title": "درس هفتم: از پاریز تا پاریس"
          },
          "8": {
            "title": "درس هشتم: نامه نگاری"
          },
          "9": {
            "title": "درس نهم: فصل شکوفایی"
          },
          "10": {
            "title": "درس دهم: نگارش علمی: مقاله نویسی 1"
          },
          "11": {
            "title": "درس یازدهم: خوان هشتم"
          },
          "12": {
            "title": "درس دوازدهم: نگارش علمی: مقاله نویسی 2"
          },
          "13": {
            "title": "درس سیزدهم: کباب غاز"
          },
          "14": {
            "title": "درس چهاردهم: خندۀ تو"
          }
        }
      }
    }
  }
}